<?xml version="1.0" encoding="UTF-8" standalone="yes"?>
<APIProxy revision="3" name="XML-Processing">
    <ConfigurationVersion majorVersion="4" minorVersion="0"/>
    <CreatedAt>1438888950446</CreatedAt>
    <CreatedBy>ravila@nearbpo.com</CreatedBy>
    <Description></Description>
    <DisplayName>XML-Processing</DisplayName>
    <LastModifiedAt>1438968380194</LastModifiedAt>
    <LastModifiedBy>ravila@nearbpo.com</LastModifiedBy>
    <Policies>
        <Policy>Check-w-query-param</Policy>
        <Policy>ExtractForecasts</Policy>
        <Policy>SetForecastsAsResponsePayload</Policy>
    </Policies>
    <ProxyEndpoints>
        <ProxyEndpoint>default</ProxyEndpoint>
    </ProxyEndpoints>
    <Resources>
        <Resource>jsc://ExtractForecasts.js</Resource>
    </Resources>
    <TargetServers/>
    <TargetEndpoints>
        <TargetEndpoint>YahooWeather</TargetEndpoint>
    </TargetEndpoints>
    <validate>false</validate>
</APIProxy>
